README
setup.py
minitestlib/Archive.py
minitestlib/Log.py
minitestlib/OrderedDict.py
minitestlib/PWSwitch.py
minitestlib/TETJournal.py
minitestlib/TestObject.py
minitestlib/Utils.py
minitestlib/WikiRPC.py
minitestlib/__init__.py
minitestlib.egg-info/PKG-INFO
minitestlib.egg-info/SOURCES.txt
minitestlib.egg-info/dependency_links.txt
minitestlib.egg-info/top_level.txt
