Metadata-Version: 1.0
Name: minitestlib
Version: 0.1.1
Summary: Library to handle TET journal files
Home-page: UNKNOWN
Author: Andy Shevchenko
Author-email: andy.shevchenko@gmail.com
License: UNKNOWN
Keywords: python test TET
Platform: Python 2.3 and later
Classifier: Development Status :: 4 - Beta
Classifier: Operating System :: Unix
Classifier: License :: OSI Approved :: BSD License
Classifier: Intended Audience :: Developers
Classifier: Programming Language :: Python
Classifier: Topic :: Software Development :: Libraries :: Python Modules
